setup.py
definitions/__init__.py
definitions/attrdict.py
definitions/error.py
definitions/parser.py
definitions.egg-info/PKG-INFO
definitions.egg-info/SOURCES.txt
definitions.egg-info/dependency_links.txt
definitions.egg-info/requires.txt
definitions.egg-info/top_level.txt
test/test_default.py
test/test_elements.py
test/test_readme.py
test/test_schema.py
test/test_type.py
test/test_use_attrdict.py