Metadata-Version: 1.0
Name: definitions
Version: 0.1.0
Summary: Load and validate YAML definitions against a schema
Home-page: http://github.com/danijar/definitions
Author: Danijar Hafner
Author-email: mail@danijar.com
License: MIT
Platform: UNKNOWN
